proxverter/__init__.py
proxverter/certgen.py
proxverter/installer.py
proxverter/sysprox.py
proxverter/plugins/__init__.py
proxverter/plugins/base.py
proxverter-0.5.3.dist-info/LICENSE
proxverter-0.5.3.dist-info/METADATA
proxverter-0.5.3.dist-info/WHEEL
proxverter-0.5.3.dist-info/top_level.txt
proxverter-0.5.3.dist-info/RECORD
